{
  "symbol": "GMX",
  "project": "GMX",
  "coingecko_id": "gmx",
  "hm_slug": "gmx",
  "updated_at": "2026-06-11T20:49:35.593Z",
  "seeded_by": "scripts/tg/seed-from-pipeline.js",
  "data_bindings": {
    "revenue": "dl_latest",
    "alignment": "hm_real_capture",
    "market": "cg_live"
  },
  "business": {
    "revenue_run_rate_window": "1y",
    "gross_revenue": 42129586,
    "buybacks_or_repurchases": null,
    "post_buyback_net_revenue": 15511569,
    "revenue_13w": 9894396,
    "durability_adjustment": 1,
    "trusted_revenue": 15511569,
    "clean_conversion": 0.85,
    "clean_platform_earnings": 13184833.65,
    "clean_conversion_grade": "A",
    "durability_score": 2,
    "business_confidence": "low"
  },
  "capital_efficiency": {
    "active_capital": null,
    "operating_treasury": null,
    "total_asset_base": null,
    "active_capital_roe": null,
    "operating_treasury_roe": null,
    "total_asset_roe": null,
    "underwriting_roe": 1.5,
    "roe_grade": "B",
    "roe_confidence": "low"
  },
  "growth": {
    "near_term_growth_score": 2,
    "durability_score": 2,
    "terminal_g": 0.02,
    "growth_grade": "C",
    "growth_confidence": "low"
  },
  "token": {
    "claim_category": "Treasury-asset claim",
    "claim_category_key": "treasury_claim",
    "token_alignment_factor": 0,
    "token_alignment_grade": "F",
    "value_capture_score": 0,
    "token_holder_rights_score": 1.5,
    "entity_alignment_score": 1,
    "transparency_score": 2,
    "token_confidence": "low"
  },
  "ke_build_up": {
    "risk_free_rate": 0.037,
    "equity_risk_premium": 0.055,
    "crypto_liquidity_premium": 0.042,
    "regulatory_premium": 0.04,
    "custody_operational_premium": 0.01,
    "governance_supply_premium": 0.014,
    "economic_alignment_premium": 0.08,
    "technical_reconciliation_premium": 0.009,
    "ke": 0.287,
    "ke_grade": "C"
  },
  "operating_cases": [
    {
      "name": "conservative",
      "post_buyback_net_revenue": 9894396,
      "clean_conversion": 0.75,
      "underwriting_roe": 1.125,
      "terminal_g": 0.01
    },
    {
      "name": "base",
      "post_buyback_net_revenue": 15511569,
      "clean_conversion": 0.85,
      "underwriting_roe": 1.5,
      "terminal_g": 0.02
    },
    {
      "name": "bull",
      "post_buyback_net_revenue": 15511569,
      "clean_conversion": 0.9,
      "underwriting_roe": 2.25,
      "terminal_g": 0.0325
    }
  ],
  "valuation": {
    "implied_full_equity": 104072287,
    "trust_discount": 1,
    "market_cap_seed": 57991233,
    "fdv_seed": 57991233,
    "ss_pe": 3.7,
    "token_attributable_earnings": 0,
    "implied_token_value": 0,
    "market_cap": 57991233,
    "fdv": 57991233,
    "market_source": "live_cg",
    "implied_value_vs_market_cap": 0,
    "implied_value_vs_fdv": 0,
    "warnings": []
  },
  "evidence": [
    {
      "field": "business.post_buyback_net_revenue",
      "claim": "Annual revenue $15.5M (DL revenue_1y); 30d-annualized $9.9M. Auto-refreshed each cron via data_bindings.",
      "source_url": "https://defillama.com/protocol/gmx",
      "confidence": "medium",
      "direction": "neutral",
      "updated_at": "2026-06-11T20:49:35.593Z"
    },
    {
      "field": "token.claim_category",
      "claim": "Derived from value-accrual metadata: buyback/paused, accrual share 1. 27% of V2 fees (30% V1) → algorithmic weekly Deposit-Buy-Withdraw cycle. Buybacks ARE executing on-chain (2M+ GMX repurchased since end-2024, verified in GMX dApp). PAUSED status = distribution suspended until GMX >= $90 (March 2026 DAO vote). Current price $6.20 = 14.5x below gate. Accumulating in Treasury.",
      "source_url": "https://defillama.com/protocol/gmx",
      "confidence": "low",
      "direction": "neutral",
      "updated_at": "2026-06-11T20:49:35.593Z"
    },
    {
      "field": "token.token_alignment_factor",
      "claim": "Alignment 0% = HM real capture $0.0M (verification: onchain_dormant) ÷ clean earnings $13.2M. Auto-refreshed each cron.",
      "source_url": "https://defillama.com/protocol/gmx",
      "confidence": "low",
      "direction": "neutral",
      "updated_at": "2026-06-11T20:49:35.593Z"
    }
  ],
  "flags": [
    "auto_seeded_from_pipeline_data"
  ],
  "scenarios": {
    "token_discount": [
      {
        "key": "no_utility",
        "category": "Current-state no utility",
        "token_alignment_factor": 0.03,
        "ke": 0.38,
        "ss_pe": 2.74,
        "token_attributable_earnings": 395545,
        "implied_token_value": 1084086
      },
      {
        "key": "soft_utility",
        "category": "Soft utility / access",
        "token_alignment_factor": 0.12,
        "ke": 0.32,
        "ss_pe": 3.29,
        "token_attributable_earnings": 1582180,
        "implied_token_value": 5203614
      },
      {
        "key": "treasury_claim",
        "category": "Treasury-asset claim",
        "token_alignment_factor": 0.35,
        "ke": 0.26,
        "ss_pe": 4.11,
        "token_attributable_earnings": 4614692,
        "implied_token_value": 18971511
      },
      {
        "key": "revenue_treasury_gov",
        "category": "Revenue + treasury governance",
        "token_alignment_factor": 0.65,
        "ke": 0.2,
        "ss_pe": 5.48,
        "token_attributable_earnings": 8570142,
        "implied_token_value": 46977074
      },
      {
        "key": "full_equity",
        "category": "Full equity / IP / token alignment",
        "token_alignment_factor": 1,
        "ke": 0.145,
        "ss_pe": 7.89,
        "token_attributable_earnings": 13184834,
        "implied_token_value": 104072287
      }
    ],
    "operating": [
      {
        "name": "conservative",
        "post_buyback_net_revenue": 9894396,
        "clean_conversion": 0.75,
        "underwriting_roe": 1.125,
        "terminal_g": 0.01,
        "clean_platform_earnings": 7420797,
        "ss_pe": 3.58,
        "implied_token_value": 0,
        "warnings": []
      },
      {
        "name": "base",
        "post_buyback_net_revenue": 15511569,
        "clean_conversion": 0.85,
        "underwriting_roe": 1.5,
        "terminal_g": 0.02,
        "clean_platform_earnings": 13184834,
        "ss_pe": 3.7,
        "implied_token_value": 0,
        "warnings": []
      },
      {
        "name": "bull",
        "post_buyback_net_revenue": 15511569,
        "clean_conversion": 0.9,
        "underwriting_roe": 2.25,
        "terminal_g": 0.0325,
        "clean_platform_earnings": 13960412,
        "ss_pe": 3.87,
        "implied_token_value": 0,
        "warnings": []
      }
    ]
  },
  "computed_at": "2026-06-12T12:15:36.912Z"
}