[
  {
    "category": "Stablecoin Issuer",
    "revenue_30d": 8429166.339508655,
    "pct": 49.4684820650438
  },
  {
    "category": "Derivatives",
    "revenue_30d": 5141231,
    "pct": 30.17248483087502
  },
  {
    "category": "Lending",
    "revenue_30d": 809417,
    "pct": 4.7502479764773
  },
  {
    "category": "Developer Tools",
    "revenue_30d": 753376,
    "pct": 4.4213586069066535
  },
  {
    "category": "Dexs",
    "revenue_30d": 531353,
    "pct": 3.1183660746502024
  },
  {
    "category": "Prediction Market",
    "revenue_30d": 205213,
    "pct": 1.2043392194589886
  },
  {
    "category": "Onchain Capital Allocator",
    "revenue_30d": 170913,
    "pct": 1.0030418590215733
  },
  {
    "category": "MEV",
    "revenue_30d": 158810,
    "pct": 0.9320126475529424
  },
  {
    "category": "RWA Lending",
    "revenue_30d": 145799,
    "pct": 0.8556546313240442
  },
  {
    "category": "CDP",
    "revenue_30d": 98939,
    "pct": 0.5806460508547358
  },
  {
    "category": "Wallets",
    "revenue_30d": 89430,
    "pct": 0.5248403190646662
  },
  {
    "category": "DEX Aggregator",
    "revenue_30d": 83061,
    "pct": 0.4874623922825701
  },
  {
    "category": "Options",
    "revenue_30d": 65856,
    "pct": 0.3864909320398374
  },
  {
    "category": "Yield",
    "revenue_30d": 62986,
    "pct": 0.36964768351344146
  },
  {
    "category": "Interest Rate Derivatives",
    "revenue_30d": 51303,
    "pct": 0.30108333768281975
  },
  {
    "category": "Bridge",
    "revenue_30d": 44114,
    "pct": 0.2588930541788962
  },
  {
    "category": "Gamified Mining",
    "revenue_30d": 43154,
    "pct": 0.25325907557773236
  },
  {
    "category": "Video Infrastructure",
    "revenue_30d": 35292,
    "pct": 0.20711913832528459
  },
  {
    "category": "Privacy",
    "revenue_30d": 27029,
    "pct": 0.158625841261309
  },
  {
    "category": "Cross Chain Bridge",
    "revenue_30d": 22180,
    "pct": 0.1301683805977222
  },
  {
    "category": "RWA",
    "revenue_30d": 12468,
    "pct": 0.073171297082615
  },
  {
    "category": "Yield Aggregator",
    "revenue_30d": 10621,
    "pct": 0.0623317570030842
  },
  {
    "category": "Liquid Restaking",
    "revenue_30d": 9026,
    "pct": 0.05297113630635891
  },
  {
    "category": "DePIN",
    "revenue_30d": 7310,
    "pct": 0.0429003995567786
  },
  {
    "category": "Trading App",
    "revenue_30d": 7078,
    "pct": 0.041538854728164015
  },
  {
    "category": "Security Extension",
    "revenue_30d": 5922,
    "pct": 0.03475460549592926
  },
  {
    "category": "Bridge Aggregator",
    "revenue_30d": 4760,
    "pct": 0.027935143897437228
  },
  {
    "category": "Launchpad",
    "revenue_30d": 3080,
    "pct": 0.01807568134540056
  },
  {
    "category": "NFT Marketplace",
    "revenue_30d": 2262,
    "pct": 0.013275062078992228
  },
  {
    "category": "Risk Curators",
    "revenue_30d": 2178,
    "pct": 0.012782088951390396
  },
  {
    "category": "Indexes",
    "revenue_30d": 2036,
    "pct": 0.011948729616634915
  },
  {
    "category": "Foundation",
    "revenue_30d": 1926,
    "pct": 0.011303169568584895
  },
  {
    "category": "Liquidity Manager",
    "revenue_30d": 962,
    "pct": 0.005645716056582902
  },
  {
    "category": "Payments",
    "revenue_30d": 516,
    "pct": 0.0030282634981255484
  },
  {
    "category": "Identity & Reputation",
    "revenue_30d": 276,
    "pct": 0.0016197688478345957
  },
  {
    "category": "Insurance",
    "revenue_30d": 154,
    "pct": 0.000903784067270028
  },
  {
    "category": "Yield Lottery",
    "revenue_30d": 106,
    "pct": 0.0006220851372118375
  },
  {
    "category": "Reserve Currency",
    "revenue_30d": 76,
    "pct": 0.00044602330592546837
  },
  {
    "category": "Basis Trading",
    "revenue_30d": 54,
    "pct": 0.00031691129631546437
  },
  {
    "category": "SoFi",
    "revenue_30d": 25,
    "pct": 0.0001467181927386409
  },
  {
    "category": "Algo-Stables",
    "revenue_30d": 6,
    "pct": 0.00003521236625727382
  },
  {
    "category": "AI Agents",
    "revenue_30d": 2,
    "pct": 0.000011737455419091273
  },
  {
    "category": "Services",
    "revenue_30d": 2,
    "pct": 0.000011737455419091273
  }
]