[
  {
    "category": "Stablecoin Issuer",
    "revenue_30d": 225010269.55228907,
    "pct": 99.37674106053146
  },
  {
    "category": "Services",
    "revenue_30d": 786380,
    "pct": 0.34730806638592243
  },
  {
    "category": "CDP",
    "revenue_30d": 483951,
    "pct": 0.21373901426223144
  },
  {
    "category": "Dexs",
    "revenue_30d": 42410,
    "pct": 0.01873055659531902
  },
  {
    "category": "Lending",
    "revenue_30d": 39995,
    "pct": 0.017663961589950112
  },
  {
    "category": "Bridge",
    "revenue_30d": 26706,
    "pct": 0.011794818307818668
  },
  {
    "category": "SoFi",
    "revenue_30d": 18011,
    "pct": 0.007954634634244067
  },
  {
    "category": "Launchpad",
    "revenue_30d": 12346,
    "pct": 0.005452663327654058
  },
  {
    "category": "RWA",
    "revenue_30d": 1393,
    "pct": 0.0006152243654156896
  }
]