[
  {
    "name": "Circle",
    "category": "Stablecoin Issuer",
    "revenue_30d": 726841.7884755059,
    "attribution": "off-chain",
    "pct_of_chain": 39.13462062248655
  },
  {
    "name": "NAVI Lending",
    "category": "Lending",
    "revenue_30d": 293998,
    "pct_of_chain": 15.8294423576026
  },
  {
    "name": "Cetus CLMM",
    "category": "Dexs",
    "revenue_30d": 107538,
    "pct_of_chain": 5.790061742773313
  },
  {
    "name": "Bluefin Spot",
    "category": "Dexs",
    "revenue_30d": 91705,
    "pct_of_chain": 4.937581246824626
  },
  {
    "name": "Bluefin Pro",
    "category": "Derivatives",
    "revenue_30d": 84053,
    "pct_of_chain": 4.525582209687043
  },
  {
    "name": "Suilend",
    "category": "Lending",
    "revenue_30d": 71594,
    "pct_of_chain": 3.8547646451683364
  },
  {
    "name": "AlphaLend",
    "category": "Lending",
    "revenue_30d": 66432,
    "pct_of_chain": 3.576832205321995
  },
  {
    "name": "Full Sail",
    "category": "Dexs",
    "revenue_30d": 53484,
    "pct_of_chain": 2.8796858994075385
  },
  {
    "name": "Haedal Protocol",
    "category": "Liquid Staking",
    "revenue_30d": 47147,
    "pct_of_chain": 2.5384891014016753
  },
  {
    "name": "Turbos",
    "category": "Dexs",
    "revenue_30d": 42885,
    "pct_of_chain": 2.3090144678051807
  },
  {
    "name": "DipCoin Perps",
    "category": "Derivatives",
    "revenue_30d": 40825,
    "pct_of_chain": 2.198099933499977
  },
  {
    "name": "Tether",
    "category": "Stablecoin Issuer",
    "revenue_30d": 38405.10548271029,
    "attribution": "off-chain",
    "pct_of_chain": 2.0678079560956544
  },
  {
    "name": "Alkimi",
    "category": "Services",
    "revenue_30d": 33777,
    "pct_of_chain": 1.8186214685567352
  },
  {
    "name": "DeepBook V3",
    "category": "Dexs",
    "revenue_30d": 28273,
    "pct_of_chain": 1.5222750623354524
  },
  {
    "name": "Momentum",
    "category": "Dexs",
    "revenue_30d": 25061,
    "pct_of_chain": 1.349334536030445
  },
  {
    "name": "Current",
    "category": "Lending",
    "revenue_30d": 21113,
    "pct_of_chain": 1.1367662926144522
  },
  {
    "name": "Scallop Lend",
    "category": "Lending",
    "revenue_30d": 18332,
    "pct_of_chain": 0.9870316713024267
  },
  {
    "name": "Bucket Protocol V2",
    "category": "CDP",
    "revenue_30d": 15733,
    "pct_of_chain": 0.8470962952542592
  },
  {
    "name": "Haedal AMM Protocol",
    "category": "Dexs",
    "revenue_30d": 11401,
    "pct_of_chain": 0.6138527211716652
  },
  {
    "name": "Cetus DLMM",
    "category": "Dexs",
    "revenue_30d": 6769,
    "pct_of_chain": 0.36445654500578917
  },
  {
    "name": "Ember Protocol",
    "category": "Onchain Capital Allocator",
    "revenue_30d": 6124,
    "pct_of_chain": 0.32972845052673255
  },
  {
    "name": "STEAMM",
    "category": "Dexs",
    "revenue_30d": 4351,
    "pct_of_chain": 0.23426657221453517
  },
  {
    "name": "FAITH Protocol",
    "category": "Gamified Mining",
    "revenue_30d": 3557,
    "pct_of_chain": 0.1915160187007818
  },
  {
    "name": "AlphaFi stSUI",
    "category": "Liquid Staking",
    "revenue_30d": 3531,
    "pct_of_chain": 0.1901161265202307
  },
  {
    "name": "KAIO",
    "category": "RWA",
    "revenue_30d": 3272,
    "pct_of_chain": 0.17617104672166378
  }
]